MANIFEST.in
requirements.txt
setup.py
lisa/__init__.py
lisa/plugins/__init__.py
lisa/plugins/BBox/README.rst
lisa/plugins/BBox/__init__.py
lisa/plugins/BBox/bbox.json
lisa/plugins/BBox/lang/fr/LC_MESSAGES/bbox.mo
lisa/plugins/BBox/lang/fr/LC_MESSAGES/bbox.po
lisa/plugins/BBox/modules/__init__.py
lisa/plugins/BBox/modules/bbox.py
lisa/plugins/BBox/web/__init__.py
lisa/plugins/BBox/web/api.py
lisa/plugins/BBox/web/models.py
lisa/plugins/BBox/web/tests.py
lisa/plugins/BBox/web/urls.py
lisa/plugins/BBox/web/views.py
lisa_plugin_BBox.egg-info/PKG-INFO
lisa_plugin_BBox.egg-info/SOURCES.txt
lisa_plugin_BBox.egg-info/dependency_links.txt
lisa_plugin_BBox.egg-info/namespace_packages.txt
lisa_plugin_BBox.egg-info/requires.txt
lisa_plugin_BBox.egg-info/top_level.txt